codeowners_backstage/__init__.py
codeowners_backstage/__main__.py
codeowners_backstage/backstage_user_groups.py
codeowners_backstage/codeowners_preprocessor.py
codeowners_backstage-0.1.3.dist-info/LICENSE
codeowners_backstage-0.1.3.dist-info/WHEEL
codeowners_backstage-0.1.3.dist-info/METADATA
codeowners_backstage-0.1.3.dist-info/RECORD
